{"path":"Ambleside%2C%20Lower%20Lake%20District","deepCounters":{"total":27,"images":27,"files":27},"counters":{"total":27,"images":27,"files":27},"thumb":{"path":"thumbs\/IMG_4029.jpeg","width":212,"height":170},"objects":[{"image":{"path":"slides\/IMG_3989.jpeg","width":1000,"height":771},"thumb":{"path":"thumbs\/IMG_3989.jpeg","width":212,"height":170},"thumbCaption":"<div class=\"title\">Swan-type ducks on Grasmere Lake, England<\/div>","photodata":"<dl><dt>Title<\/dt><dd>Swan-type ducks on Grasmere Lake, England<\/dd><dt>Original Date<\/dt><dd>7\/13\/24, 11:38 AM<\/dd><dt>Make<\/dt><dd>Apple<\/dd><dt>Camera<\/dt><dd>iPhone 15 Pro Max<\/dd><dt>Lens Model<\/dt><dd>iPhone 15 Pro Max back triple camera 15.66mm f\/2.8<\/dd><dt>Focal Length (35mm)<\/dt><dd>121mm<\/dd><dt>Metering Mode<\/dt><dd>Multi-segment<\/dd><dt>ISO Equivalent<\/dt><dd>50<\/dd><dt>Exposure Time<\/dt><dd>1\/450s<\/dd><dt>Aperture<\/dt><dd>ƒ\/2.8<\/dd><dt>Exposure bias<\/dt><dd>0 EV<\/dd><dt>Exposure Program<\/dt><dd>Program normal<\/dd><dt>White balance<\/dt><dd>Auto white balance<\/dd><dt>Flash<\/dt><dd>Flash did not fire<\/dd><dt>Resolution<\/dt><dd>2893 x 2231<\/dd><\/dl>","dates":{"dateTaken":1720895887},"fileDate":"2024-07-29T10:41:32.590Z","title":"Swan-type ducks on Grasmere Lake, England","path":"IMG_3989.jpeg","imageCaption":"<div class=\"title\">Swan-type ducks on Grasmere Lake, England<\/div>","fileSize":466746,"name":"IMG_3989.jpeg","category":"image","camera":{"aperture":2.8,"exposureTime":"1\/450s","originalDate":"2024-07-13T11:38:07.0Z","cameraModel":"iPhone 15 Pro Max","location":{"altitude":"39.24 metres","latitude":"54° 25' 15.39\"","lat":54.42094,"long":-2.963136,"longitude":"-2° 57' 47.29\""},"focalLength35mm":"121mm","resolution":"2893 x 2231","cameraMake":"Apple","isoEquivalent":50,"flash":"Flash did not fire","focalLength":"16mm"}},{"path":"IMG_3991.jpeg","image":{"path":"slides\/IMG_3991.jpeg","width":1000,"height":750},"thumb":{"path":"thumbs\/IMG_3991.jpeg","width":212,"height":170},"fileSize":342396,"photodata":"<dl><dt>Original Date<\/dt><dd>7\/13\/24, 11:40 AM<\/dd><dt>Make<\/dt><dd>Apple<\/dd><dt>Camera<\/dt><dd>iPhone 15 Pro Max<\/dd><dt>Lens Model<\/dt><dd>iPhone 15 Pro Max back triple camera 6.765mm f\/1.78<\/dd><dt>Focal Length (35mm)<\/dt><dd>36mm<\/dd><dt>Metering Mode<\/dt><dd>Multi-segment<\/dd><dt>ISO Equivalent<\/dt><dd>80<\/dd><dt>Exposure Time<\/dt><dd>1\/2331s<\/dd><dt>Aperture<\/dt><dd>ƒ\/1.8<\/dd><dt>Exposure bias<\/dt><dd>0 EV<\/dd><dt>Exposure Program<\/dt><dd>Program normal<\/dd><dt>White balance<\/dt><dd>Auto white balance<\/dd><dt>Flash<\/dt><dd>Flash did not fire<\/dd><dt>Resolution<\/dt><dd>5712 x 4284<\/dd><\/dl>","name":"IMG_3991.jpeg","dates":{"dateTaken":1720896000},"fileDate":"2024-07-29T10:41:32.639Z","category":"image","camera":{"aperture":1.78,"exposureTime":"1\/2331s","originalDate":"2024-07-13T11:40:00.0Z","cameraModel":"iPhone 15 Pro Max","location":{"altitude":"41.84 metres","latitude":"54° 25' 12.93\"","lat":54.420258,"long":-2.962181,"longitude":"-2° 57' 43.85\""},"focalLength35mm":"36mm","resolution":"5712 x 4284","cameraMake":"Apple","isoEquivalent":80,"flash":"Flash did not fire","focalLength":"7mm"}},{"path":"IMG_4001.jpeg","image":{"path":"slides\/IMG_4001.jpeg","width":636,"height":800},"thumb":{"path":"thumbs\/IMG_4001.jpeg","width":212,"height":170},"fileSize":176953,"photodata":"<dl><dt>Original Date<\/dt><dd>7\/13\/24, 12:29 PM<\/dd><dt>Make<\/dt><dd>Apple<\/dd><dt>Camera<\/dt><dd>iPhone 15 Pro Max<\/dd><dt>Lens Model<\/dt><dd>iPhone 15 Pro Max back triple camera 6.765mm f\/1.78<\/dd><dt>Focal Length (35mm)<\/dt><dd>49mm<\/dd><dt>Metering Mode<\/dt><dd>Multi-segment<\/dd><dt>ISO Equivalent<\/dt><dd>64<\/dd><dt>Exposure Time<\/dt><dd>1\/5848s<\/dd><dt>Aperture<\/dt><dd>ƒ\/1.8<\/dd><dt>Exposure bias<\/dt><dd>0 EV<\/dd><dt>Exposure Program<\/dt><dd>Program normal<\/dd><dt>White balance<\/dt><dd>Auto white balance<\/dd><dt>Flash<\/dt><dd>Flash did not fire<\/dd><dt>Resolution<\/dt><dd>4032 x 3024<\/dd><\/dl>","name":"IMG_4001.jpeg","dates":{"dateTaken":1720898944},"fileDate":"2024-07-29T10:41:32.750Z","category":"image","camera":{"aperture":1.78,"exposureTime":"1\/5848s","originalDate":"2024-07-13T12:29:04.0Z","cameraModel":"iPhone 15 Pro Max","location":{"altitude":"38.21 metres","latitude":"54° 24' 22.64\"","lat":54.40629,"long":-2.961614,"longitude":"-2° 57' 41.81\""},"focalLength35mm":"49mm","resolution":"4032 x 3024","cameraMake":"Apple","isoEquivalent":64,"flash":"Flash did not fire","focalLength":"7mm"}},{"path":"IMG_4052.jpeg","image":{"path":"slides\/IMG_4052.jpeg","width":600,"height":800},"thumb":{"path":"thumbs\/IMG_4052.jpeg","width":212,"height":170},"fileSize":277383,"photodata":"<dl><dt>Original Date<\/dt><dd>7\/14\/24, 8:06 AM<\/dd><dt>Make<\/dt><dd>Apple<\/dd><dt>Camera<\/dt><dd>iPhone 15 Pro Max<\/dd><dt>Lens Model<\/dt><dd>iPhone 15 Pro Max back triple camera 6.765mm f\/1.78<\/dd><dt>Focal Length (35mm)<\/dt><dd>40mm<\/dd><dt>Metering Mode<\/dt><dd>Multi-segment<\/dd><dt>ISO Equivalent<\/dt><dd>100<\/dd><dt>Exposure Time<\/dt><dd>1\/121s<\/dd><dt>Aperture<\/dt><dd>ƒ\/1.8<\/dd><dt>Exposure bias<\/dt><dd>0 EV<\/dd><dt>Exposure Program<\/dt><dd>Program normal<\/dd><dt>White balance<\/dt><dd>Auto white balance<\/dd><dt>Flash<\/dt><dd>Flash did not fire<\/dd><dt>Resolution<\/dt><dd>5712 x 4284<\/dd><\/dl>","name":"IMG_4052.jpeg","dates":{"dateTaken":1720969563},"fileDate":"2024-07-29T10:41:33.669Z","category":"image","camera":{"aperture":1.78,"exposureTime":"1\/121s","originalDate":"2024-07-14T08:06:03.0Z","cameraModel":"iPhone 15 Pro Max","location":{"altitude":"42.41 metres","latitude":"54° 25' 16.62\"","lat":54.421284,"long":-2.963436,"longitude":"-2° 57' 48.37\""},"focalLength35mm":"40mm","resolution":"5712 x 4284","cameraMake":"Apple","isoEquivalent":100,"flash":"Flash did not fire","focalLength":"7mm"}},{"image":{"path":"slides\/IMG_4078.jpeg","width":600,"height":800},"thumb":{"path":"thumbs\/IMG_4078.jpeg","width":212,"height":170},"thumbCaption":"<div class=\"title\">Down the stairs to our room...<\/div>","photodata":"<dl><dt>Title<\/dt><dd>Down the stairs to our room...<\/dd><dt>Original Date<\/dt><dd>7\/14\/24, 11:06 AM<\/dd><dt>Make<\/dt><dd>Apple<\/dd><dt>Camera<\/dt><dd>iPhone 15 Pro Max<\/dd><dt>Lens Model<\/dt><dd>iPhone 15 Pro Max back triple camera 2.22mm f\/2.2<\/dd><dt>Focal Length (35mm)<\/dt><dd>14mm<\/dd><dt>Metering Mode<\/dt><dd>Multi-segment<\/dd><dt>ISO Equivalent<\/dt><dd>200<\/dd><dt>Exposure Time<\/dt><dd>1\/100s<\/dd><dt>Aperture<\/dt><dd>ƒ\/2.2<\/dd><dt>Exposure bias<\/dt><dd>0 EV<\/dd><dt>Exposure Program<\/dt><dd>Program normal<\/dd><dt>White balance<\/dt><dd>Auto white balance<\/dd><dt>Flash<\/dt><dd>Flash did not fire<\/dd><dt>Resolution<\/dt><dd>4032 x 3024<\/dd><\/dl>","dates":{"dateTaken":1720980370},"fileDate":"2024-07-29T10:41:33.710Z","title":"Down the stairs to our room...","path":"IMG_4078.jpeg","imageCaption":"<div class=\"title\">Down the stairs to our room...<\/div>","fileSize":200269,"name":"IMG_4078.jpeg","category":"image","camera":{"aperture":2.2,"exposureTime":"1\/100s","originalDate":"2024-07-14T11:06:10.0Z","cameraModel":"iPhone 15 Pro Max","location":{"altitude":"43.9 metres","latitude":"54° 25' 16.91\"","lat":54.421364,"long":-2.963189,"longitude":"-2° 57' 47.48\""},"focalLength35mm":"14mm","resolution":"4032 x 3024","cameraMake":"Apple","isoEquivalent":200,"flash":"Flash did not fire","focalLength":"2mm"}},{"image":{"path":"slides\/IMG_4079.jpeg","width":600,"height":800},"thumb":{"path":"thumbs\/IMG_4079.jpeg","width":212,"height":170},"thumbCaption":"<div class=\"title\">Up the stairs to our room...<\/div>","photodata":"<dl><dt>Title<\/dt><dd>Up the stairs to our room...<\/dd><dt>Original Date<\/dt><dd>7\/14\/24, 11:06 AM<\/dd><dt>Make<\/dt><dd>Apple<\/dd><dt>Camera<\/dt><dd>iPhone 15 Pro Max<\/dd><dt>Lens Model<\/dt><dd>iPhone 15 Pro Max back triple camera 2.22mm f\/2.2<\/dd><dt>Focal Length (35mm)<\/dt><dd>14mm<\/dd><dt>Metering Mode<\/dt><dd>Multi-segment<\/dd><dt>ISO Equivalent<\/dt><dd>500<\/dd><dt>Exposure Time<\/dt><dd>1\/50s<\/dd><dt>Aperture<\/dt><dd>ƒ\/2.2<\/dd><dt>Exposure bias<\/dt><dd>0 EV<\/dd><dt>Exposure Program<\/dt><dd>Program normal<\/dd><dt>White balance<\/dt><dd>Auto white balance<\/dd><dt>Flash<\/dt><dd>Flash did not fire<\/dd><dt>Resolution<\/dt><dd>4032 x 3024<\/dd><\/dl>","dates":{"dateTaken":1720980399},"fileDate":"2024-07-29T10:41:33.730Z","title":"Up the stairs to our room...","path":"IMG_4079.jpeg","imageCaption":"<div class=\"title\">Up the stairs to our room...<\/div>","fileSize":172462,"name":"IMG_4079.jpeg","category":"image","camera":{"aperture":2.2,"exposureTime":"1\/50s","originalDate":"2024-07-14T11:06:39.0Z","cameraModel":"iPhone 15 Pro Max","location":{"altitude":"43.17 metres","latitude":"54° 25' 16.74\"","lat":54.421318,"long":-2.963239,"longitude":"-2° 57' 47.66\""},"focalLength35mm":"14mm","resolution":"4032 x 3024","cameraMake":"Apple","isoEquivalent":500,"flash":"Flash did not fire","focalLength":"2mm"}},{"image":{"path":"slides\/IMG_4080.jpeg","width":600,"height":800},"thumb":{"path":"thumbs\/IMG_4080.jpeg","width":212,"height":170},"thumbCaption":"<div class=\"title\">Serious duck-age here...<\/div>","photodata":"<dl><dt>Title<\/dt><dd>Serious duck-age here...<\/dd><dt>Original Date<\/dt><dd>7\/14\/24, 11:06 AM<\/dd><dt>Make<\/dt><dd>Apple<\/dd><dt>Camera<\/dt><dd>iPhone 15 Pro Max<\/dd><dt>Lens Model<\/dt><dd>iPhone 15 Pro Max back triple camera 2.22mm f\/2.2<\/dd><dt>Focal Length (35mm)<\/dt><dd>14mm<\/dd><dt>Metering Mode<\/dt><dd>Multi-segment<\/dd><dt>ISO Equivalent<\/dt><dd>320<\/dd><dt>Exposure Time<\/dt><dd>1\/50s<\/dd><dt>Aperture<\/dt><dd>ƒ\/2.2<\/dd><dt>Exposure bias<\/dt><dd>0 EV<\/dd><dt>Exposure Program<\/dt><dd>Program normal<\/dd><dt>White balance<\/dt><dd>Auto white balance<\/dd><dt>Flash<\/dt><dd>Flash did not fire<\/dd><dt>Resolution<\/dt><dd>4032 x 3024<\/dd><\/dl>","dates":{"dateTaken":1720980407},"fileDate":"2024-07-29T10:41:33.750Z","title":"Serious duck-age here...","path":"IMG_4080.jpeg","imageCaption":"<div class=\"title\">Serious duck-age here...<\/div>","fileSize":194679,"name":"IMG_4080.jpeg","category":"image","camera":{"aperture":2.2,"exposureTime":"1\/50s","originalDate":"2024-07-14T11:06:47.0Z","cameraModel":"iPhone 15 Pro Max","location":{"altitude":"43.13 metres","latitude":"54° 25' 16.81\"","lat":54.421337,"long":-2.963311,"longitude":"-2° 57' 47.92\""},"focalLength35mm":"14mm","resolution":"4032 x 3024","cameraMake":"Apple","isoEquivalent":320,"flash":"Flash did not fire","focalLength":"2mm"}},{"image":{"path":"slides\/IMG_4082.jpeg","width":1000,"height":363},"thumb":{"path":"thumbs\/IMG_4082.jpeg","width":212,"height":170},"thumbCaption":"<div class=\"title\">View from the third room we had in three days...<\/div>","photodata":"<dl><dt>Title<\/dt><dd>View from the third room we had in three days...<\/dd><dt>Original Date<\/dt><dd>7\/14\/24, 1:36 PM<\/dd><dt>Make<\/dt><dd>Apple<\/dd><dt>Camera<\/dt><dd>iPhone 15 Pro Max<\/dd><dt>Lens Model<\/dt><dd>iPhone 15 Pro Max back triple camera 2.22mm f\/2.2<\/dd><dt>Focal Length (35mm)<\/dt><dd>17mm<\/dd><dt>Metering Mode<\/dt><dd>Multi-segment<\/dd><dt>ISO Equivalent<\/dt><dd>50<\/dd><dt>Exposure Time<\/dt><dd>1\/1567s<\/dd><dt>Aperture<\/dt><dd>ƒ\/2.2<\/dd><dt>Exposure bias<\/dt><dd>0 EV<\/dd><dt>Exposure Program<\/dt><dd>Program normal<\/dd><dt>White balance<\/dt><dd>Auto white balance<\/dd><dt>Flash<\/dt><dd>Flash did not fire<\/dd><dt>Resolution<\/dt><dd>4032 x 1465<\/dd><\/dl>","dates":{"dateTaken":1720989383},"fileDate":"2024-07-29T10:41:33.809Z","title":"View from the third room we had in three days...","path":"IMG_4082.jpeg","imageCaption":"<div class=\"title\">View from the third room we had in three days...<\/div>","fileSize":760548,"name":"IMG_4082.jpeg","category":"image","camera":{"aperture":2.2,"exposureTime":"1\/1567s","originalDate":"2024-07-14T13:36:23.0Z","cameraModel":"iPhone 15 Pro Max","location":{"altitude":"48.2 metres","latitude":"54° 25' 18.04\"","lat":54.421677,"long":-2.963517,"longitude":"-2° 57' 48.66\""},"focalLength35mm":"17mm","resolution":"4032 x 1465","cameraMake":"Apple","isoEquivalent":50,"flash":"Flash did not fire","focalLength":"2mm"}},{"image":{"path":"slides\/IMG_4049.jpeg","width":1000,"height":721},"thumb":{"path":"thumbs\/IMG_4049.jpeg","width":212,"height":170},"thumbCaption":"<div class=\"title\">Restaurant in town...<\/div>","photodata":"<dl><dt>Title<\/dt><dd>Restaurant in town...<\/dd><dt>Original Date<\/dt><dd>7\/13\/24, 6:13 PM<\/dd><dt>Make<\/dt><dd>Apple<\/dd><dt>Camera<\/dt><dd>iPhone 15 Pro Max<\/dd><dt>Lens Model<\/dt><dd>iPhone 15 Pro Max back triple camera 2.22mm f\/2.2<\/dd><dt>Focal Length (35mm)<\/dt><dd>24mm<\/dd><dt>Metering Mode<\/dt><dd>Multi-segment<\/dd><dt>ISO Equivalent<\/dt><dd>500<\/dd><dt>Exposure Time<\/dt><dd>1\/50s<\/dd><dt>Aperture<\/dt><dd>ƒ\/2.2<\/dd><dt>Exposure bias<\/dt><dd>0 EV<\/dd><dt>Exposure Program<\/dt><dd>Program normal<\/dd><dt>White balance<\/dt><dd>Auto white balance<\/dd><dt>Flash<\/dt><dd>Flash did not fire<\/dd><dt>Resolution<\/dt><dd>2745 x 1979<\/dd><\/dl>","dates":{"dateTaken":1720919603},"fileDate":"2024-07-29T10:41:33.629Z","title":"Restaurant in town...","path":"IMG_4049.jpeg","imageCaption":"<div class=\"title\">Restaurant in town...<\/div>","fileSize":459973,"name":"IMG_4049.jpeg","category":"image","camera":{"aperture":2.2,"exposureTime":"1\/50s","originalDate":"2024-07-13T18:13:23.0Z","cameraModel":"iPhone 15 Pro Max","location":{"altitude":"57.75 metres","latitude":"54° 25' 51.05\"","lat":54.430847,"long":-2.962408,"longitude":"-2° 57' 44.67\""},"focalLength35mm":"24mm","resolution":"2745 x 1979","cameraMake":"Apple","isoEquivalent":500,"flash":"Flash did not fire","focalLength":"2mm"}},{"image":{"path":"slides\/IMG_4002.jpeg","width":1000,"height":750},"thumb":{"path":"thumbs\/IMG_4002.jpeg","width":212,"height":170},"thumbCaption":"<div class=\"title\">Ferry ride to Wray Castle<\/div>","photodata":"<dl><dt>Title<\/dt><dd>Ferry ride to Wray Castle<\/dd><dt>Original Date<\/dt><dd>7\/13\/24, 12:29 PM<\/dd><dt>Make<\/dt><dd>Apple<\/dd><dt>Camera<\/dt><dd>iPhone 15 Pro Max<\/dd><dt>Lens Model<\/dt><dd>iPhone 15 Pro Max back triple camera 15.66mm f\/2.8<\/dd><dt>Focal Length (35mm)<\/dt><dd>138mm<\/dd><dt>Metering Mode<\/dt><dd>Multi-segment<\/dd><dt>ISO Equivalent<\/dt><dd>50<\/dd><dt>Exposure Time<\/dt><dd>1\/1048s<\/dd><dt>Aperture<\/dt><dd>ƒ\/2.8<\/dd><dt>Exposure bias<\/dt><dd>0 EV<\/dd><dt>Exposure Program<\/dt><dd>Program normal<\/dd><dt>White balance<\/dt><dd>Auto white balance<\/dd><dt>Flash<\/dt><dd>Flash did not fire<\/dd><dt>Resolution<\/dt><dd>4032 x 3024<\/dd><\/dl>","dates":{"dateTaken":1720898974},"fileDate":"2024-07-29T10:41:32.779Z","title":"Ferry ride to Wray Castle","path":"IMG_4002.jpeg","imageCaption":"<div class=\"title\">Ferry ride to Wray Castle<\/div>","fileSize":491138,"name":"IMG_4002.jpeg","category":"image","camera":{"aperture":2.8,"exposureTime":"1\/1048s","originalDate":"2024-07-13T12:29:34.0Z","cameraModel":"iPhone 15 Pro Max","location":{"altitude":"39.87 metres","latitude":"54° 24' 19.64\"","lat":54.405457,"long":-2.960644,"longitude":"-2° 57' 38.32\""},"focalLength35mm":"138mm","resolution":"4032 x 3024","cameraMake":"Apple","isoEquivalent":50,"flash":"Flash did not fire","focalLength":"16mm"}},{"image":{"path":"slides\/IMG_4003.jpeg","width":600,"height":800},"thumb":{"path":"thumbs\/IMG_4003.jpeg","width":212,"height":170},"thumbCaption":"<div class=\"title\">The walk up to the castle...<\/div>","photodata":"<dl><dt>Title<\/dt><dd>The walk up to the castle...<\/dd><dt>Original Date<\/dt><dd>7\/13\/24, 12:36 PM<\/dd><dt>Make<\/dt><dd>Apple<\/dd><dt>Camera<\/dt><dd>iPhone 15 Pro Max<\/dd><dt>Lens Model<\/dt><dd>iPhone 15 Pro Max back triple camera 6.765mm f\/1.78<\/dd><dt>Focal Length (35mm)<\/dt><dd>53mm<\/dd><dt>Metering Mode<\/dt><dd>Multi-segment<\/dd><dt>ISO Equivalent<\/dt><dd>64<\/dd><dt>Exposure Time<\/dt><dd>1\/966s<\/dd><dt>Aperture<\/dt><dd>ƒ\/1.8<\/dd><dt>Exposure bias<\/dt><dd>0 EV<\/dd><dt>Exposure Program<\/dt><dd>Program normal<\/dd><dt>White balance<\/dt><dd>Auto white balance<\/dd><dt>Flash<\/dt><dd>Flash did not fire<\/dd><dt>Resolution<\/dt><dd>4032 x 3024<\/dd><\/dl>","dates":{"dateTaken":1720899386},"fileDate":"2024-07-29T10:41:32.809Z","title":"The walk up to the castle...","path":"IMG_4003.jpeg","imageCaption":"<div class=\"title\">The walk up to the castle...<\/div>","fileSize":360010,"name":"IMG_4003.jpeg","category":"image","camera":{"aperture":1.78,"exposureTime":"1\/966s","originalDate":"2024-07-13T12:36:26.0Z","cameraModel":"iPhone 15 Pro Max","location":{"altitude":"53.13 metres","latitude":"54° 24' 7.78\"","lat":54.40216,"long":-2.964178,"longitude":"-2° 57' 51.04\""},"focalLength35mm":"53mm","resolution":"4032 x 3024","cameraMake":"Apple","isoEquivalent":64,"flash":"Flash did not fire","focalLength":"7mm"}},{"path":"IMG_4012.jpeg","image":{"path":"slides\/IMG_4012.jpeg","width":611,"height":677},"thumb":{"path":"thumbs\/IMG_4012.jpeg","width":212,"height":170},"fileSize":456987,"photodata":"<dl><dt>Original Date<\/dt><dd>7\/13\/24, 12:55 PM<\/dd><dt>Make<\/dt><dd>Apple<\/dd><dt>Camera<\/dt><dd>iPhone 15 Pro Max<\/dd><dt>Lens Model<\/dt><dd>iPhone 15 Pro Max back triple camera 6.765mm f\/1.78<\/dd><dt>Focal Length (35mm)<\/dt><dd>33mm<\/dd><dt>Metering Mode<\/dt><dd>Multi-segment<\/dd><dt>ISO Equivalent<\/dt><dd>200<\/dd><dt>Exposure Time<\/dt><dd>1\/100s<\/dd><dt>Aperture<\/dt><dd>ƒ\/1.8<\/dd><dt>Exposure bias<\/dt><dd>0 EV<\/dd><dt>Exposure Program<\/dt><dd>Program normal<\/dd><dt>White balance<\/dt><dd>Auto white balance<\/dd><dt>Flash<\/dt><dd>Flash did not fire<\/dd><dt>Resolution<\/dt><dd>5712 x 4284<\/dd><\/dl>","name":"IMG_4012.jpeg","dates":{"dateTaken":1720900509},"fileDate":"2024-07-29T10:40:48.960Z","category":"image","camera":{"aperture":1.78,"exposureTime":"1\/100s","originalDate":"2024-07-13T12:55:09.0Z","cameraModel":"iPhone 15 Pro Max","location":{"altitude":"76.91 metres","latitude":"54° 24' 26.58\"","lat":54.407383,"long":-2.950464,"longitude":"-2° 57' 1.67\""},"focalLength35mm":"33mm","resolution":"5712 x 4284","cameraMake":"Apple","isoEquivalent":200,"flash":"Flash did not fire","focalLength":"7mm"}},{"path":"IMG_4005.jpeg","image":{"path":"slides\/IMG_4005.jpeg","width":600,"height":800},"thumb":{"path":"thumbs\/IMG_4005.jpeg","width":212,"height":170},"fileSize":375951,"photodata":"<dl><dt>Original Date<\/dt><dd>7\/13\/24, 12:37 PM<\/dd><dt>Make<\/dt><dd>Apple<\/dd><dt>Camera<\/dt><dd>iPhone 15 Pro Max<\/dd><dt>Lens Model<\/dt><dd>iPhone 15 Pro Max back triple camera 6.765mm f\/1.78<\/dd><dt>Focal Length (35mm)<\/dt><dd>46mm<\/dd><dt>Metering Mode<\/dt><dd>Multi-segment<\/dd><dt>ISO Equivalent<\/dt><dd>80<\/dd><dt>Exposure Time<\/dt><dd>1\/1818s<\/dd><dt>Aperture<\/dt><dd>ƒ\/1.8<\/dd><dt>Exposure bias<\/dt><dd>0 EV<\/dd><dt>Exposure Program<\/dt><dd>Program normal<\/dd><dt>White balance<\/dt><dd>Auto white balance<\/dd><dt>Flash<\/dt><dd>Flash did not fire<\/dd><dt>Resolution<\/dt><dd>5712 x 4284<\/dd><\/dl>","name":"IMG_4005.jpeg","dates":{"dateTaken":1720899449},"fileDate":"2024-07-29T10:41:32.899Z","category":"image","camera":{"aperture":1.78,"exposureTime":"1\/1818s","originalDate":"2024-07-13T12:37:29.0Z","cameraModel":"iPhone 15 Pro Max","location":{"altitude":"64.66 metres","latitude":"54° 24' 4.87\"","lat":54.401352,"long":-2.963911,"longitude":"-2° 57' 50.08\""},"focalLength35mm":"46mm","resolution":"5712 x 4284","cameraMake":"Apple","isoEquivalent":80,"flash":"Flash did not fire","focalLength":"7mm"}},{"image":{"path":"slides\/IMG_4006.jpeg","width":1000,"height":750},"regions":"[\";0.699;0.301;0.031;0.041\",\";0.480;0.264;0.029;0.040\",\";0.430;0.488;0.030;0.040\",\";0.309;0.516;0.028;0.038\",\";0.077;0.246;0.034;0.045\",\";0.148;0.218;0.031;0.042\"]","thumb":{"path":"thumbs\/IMG_4006.jpeg","width":212,"height":170},"thumbCaption":"<div class=\"title\">Turns out to be a fake castle, built in the late 1800's, by a rich mountaineering enthusiast... <\/div>","photodata":"<dl><dt>Title<\/dt><dd>Turns out to be a fake castle, built in the late 1800's, by a rich mountaineering enthusiast... <\/dd><dt>Original Date<\/dt><dd>7\/13\/24, 12:45 PM<\/dd><dt>Make<\/dt><dd>Apple<\/dd><dt>Camera<\/dt><dd>iPhone 15 Pro Max<\/dd><dt>Lens Model<\/dt><dd>iPhone 15 Pro Max back triple camera 6.765mm f\/1.78<\/dd><dt>Focal Length (35mm)<\/dt><dd>24mm<\/dd><dt>Metering Mode<\/dt><dd>Multi-segment<\/dd><dt>ISO Equivalent<\/dt><dd>80<\/dd><dt>Exposure Time<\/dt><dd>1\/100s<\/dd><dt>Aperture<\/dt><dd>ƒ\/1.8<\/dd><dt>Exposure bias<\/dt><dd>0 EV<\/dd><dt>Exposure Program<\/dt><dd>Program normal<\/dd><dt>White balance<\/dt><dd>Auto white balance<\/dd><dt>Flash<\/dt><dd>Flash did not fire<\/dd><dt>Resolution<\/dt><dd>5712 x 4284<\/dd><\/dl>","dates":{"dateTaken":1720899923},"fileDate":"2024-07-29T10:41:32.960Z","title":"Turns out to be a fake castle, built in the late 1800's, by a rich mountaineering enthusiast... ","path":"IMG_4006.jpeg","imageCaption":"<div class=\"title\">Turns out to be a fake castle, built in the late 1800's, by a rich mountaineering enthusiast... <\/div>","fileSize":538363,"name":"IMG_4006.jpeg","category":"image","camera":{"aperture":1.78,"exposureTime":"1\/100s","originalDate":"2024-07-13T12:45:23.0Z","cameraModel":"iPhone 15 Pro Max","location":{"altitude":"67.83 metres","latitude":"54° 24' 2.9\"","lat":54.400806,"long":-2.964442,"longitude":"-2° 57' 51.99\""},"focalLength35mm":"24mm","resolution":"5712 x 4284","cameraMake":"Apple","isoEquivalent":80,"flash":"Flash did not fire","focalLength":"7mm"}},{"image":{"path":"slides\/IMG_4007.jpeg","width":600,"height":800},"thumb":{"path":"thumbs\/IMG_4007.jpeg","width":212,"height":170},"thumbCaption":"<div class=\"title\">The entire castle is a museum to mountaineering in the early 1900's.<\/div>","photodata":"<dl><dt>Title<\/dt><dd>The entire castle is a museum to mountaineering in the early 1900's.<\/dd><dt>Original Date<\/dt><dd>7\/13\/24, 12:45 PM<\/dd><dt>Make<\/dt><dd>Apple<\/dd><dt>Camera<\/dt><dd>iPhone 15 Pro Max<\/dd><dt>Lens Model<\/dt><dd>iPhone 15 Pro Max back triple camera 6.765mm f\/1.78<\/dd><dt>Focal Length (35mm)<\/dt><dd>121mm<\/dd><dt>Metering Mode<\/dt><dd>Multi-segment<\/dd><dt>ISO Equivalent<\/dt><dd>160<\/dd><dt>Exposure Time<\/dt><dd>1\/50s<\/dd><dt>Aperture<\/dt><dd>ƒ\/1.8<\/dd><dt>Exposure bias<\/dt><dd>0 EV<\/dd><dt>Exposure Program<\/dt><dd>Program normal<\/dd><dt>White balance<\/dt><dd>Auto white balance<\/dd><dt>Flash<\/dt><dd>Flash did not fire<\/dd><dt>Resolution<\/dt><dd>4032 x 3024<\/dd><\/dl>","dates":{"dateTaken":1720899931},"fileDate":"2024-07-29T10:41:32.990Z","title":"The entire castle is a museum to mountaineering in the early 1900's.","path":"IMG_4007.jpeg","imageCaption":"<div class=\"title\">The entire castle is a museum to mountaineering in the early 1900's.<\/div>","fileSize":242879,"name":"IMG_4007.jpeg","category":"image","camera":{"aperture":1.78,"exposureTime":"1\/50s","originalDate":"2024-07-13T12:45:31.0Z","cameraModel":"iPhone 15 Pro Max","location":{"altitude":"70.8 metres","latitude":"54° 24' 2.89\"","lat":54.400803,"long":-2.964425,"longitude":"-2° 57' 51.93\""},"focalLength35mm":"121mm","resolution":"4032 x 3024","cameraMake":"Apple","isoEquivalent":160,"flash":"Flash did not fire","focalLength":"7mm"}},{"image":{"path":"slides\/IMG_4008.jpeg","width":1000,"height":750},"regions":"[\";0.736;0.457;0.042;0.058\",\";0.235;0.440;0.063;0.084\",\";0.451;0.440;0.063;0.084\"]","thumb":{"path":"thumbs\/IMG_4008.jpeg","width":212,"height":170},"thumbCaption":"<div class=\"title\">Mostly Tibet...<\/div>","photodata":"<dl><dt>Title<\/dt><dd>Mostly Tibet...<\/dd><dt>Original Date<\/dt><dd>7\/13\/24, 12:45 PM<\/dd><dt>Make<\/dt><dd>Apple<\/dd><dt>Camera<\/dt><dd>iPhone 15 Pro Max<\/dd><dt>Lens Model<\/dt><dd>iPhone 15 Pro Max back triple camera 6.765mm f\/1.78<\/dd><dt>Focal Length (35mm)<\/dt><dd>36mm<\/dd><dt>Metering Mode<\/dt><dd>Multi-segment<\/dd><dt>ISO Equivalent<\/dt><dd>80<\/dd><dt>Exposure Time<\/dt><dd>1\/100s<\/dd><dt>Aperture<\/dt><dd>ƒ\/1.8<\/dd><dt>Exposure bias<\/dt><dd>0 EV<\/dd><dt>Exposure Program<\/dt><dd>Program normal<\/dd><dt>White balance<\/dt><dd>Auto white balance<\/dd><dt>Flash<\/dt><dd>Flash did not fire<\/dd><dt>Resolution<\/dt><dd>5712 x 4284<\/dd><\/dl>","dates":{"dateTaken":1720899942},"fileDate":"2024-07-29T10:41:33.29Z","title":"Mostly Tibet...","path":"IMG_4008.jpeg","imageCaption":"<div class=\"title\">Mostly Tibet...<\/div>","fileSize":448788,"name":"IMG_4008.jpeg","category":"image","camera":{"aperture":1.78,"exposureTime":"1\/100s","originalDate":"2024-07-13T12:45:42.0Z","cameraModel":"iPhone 15 Pro Max","location":{"altitude":"73.71 metres","latitude":"54° 24' 2.92\"","lat":54.40081,"long":-2.964472,"longitude":"-2° 57' 52.1\""},"focalLength35mm":"36mm","resolution":"5712 x 4284","cameraMake":"Apple","isoEquivalent":80,"flash":"Flash did not fire","focalLength":"7mm"}},{"image":{"path":"slides\/IMG_4010.jpeg","width":599,"height":800},"regions":"[\";0.909;0.873;0.091;0.127\"]","thumb":{"path":"thumbs\/IMG_4010.jpeg","width":212,"height":170},"thumbCaption":"<div class=\"title\">The Yeti made an appearance...<\/div>","photodata":"<dl><dt>Title<\/dt><dd>The Yeti made an appearance...<\/dd><dt>Original Date<\/dt><dd>7\/13\/24, 12:51 PM<\/dd><dt>Make<\/dt><dd>Apple<\/dd><dt>Camera<\/dt><dd>iPhone 15 Pro Max<\/dd><dt>Lens Model<\/dt><dd>iPhone 15 Pro Max back triple camera 6.765mm f\/1.78<\/dd><dt>Focal Length (35mm)<\/dt><dd>33mm<\/dd><dt>Metering Mode<\/dt><dd>Spot<\/dd><dt>ISO Equivalent<\/dt><dd>250<\/dd><dt>Exposure Time<\/dt><dd>1\/60s<\/dd><dt>Aperture<\/dt><dd>ƒ\/1.8<\/dd><dt>Exposure bias<\/dt><dd>0 EV<\/dd><dt>Exposure Program<\/dt><dd>Program normal<\/dd><dt>White balance<\/dt><dd>Auto white balance<\/dd><dt>Flash<\/dt><dd>Flash did not fire<\/dd><dt>Resolution<\/dt><dd>4284 x 5712<\/dd><\/dl>","dates":{"dateTaken":1720900283},"fileDate":"2024-07-29T10:41:33.129Z","title":"The Yeti made an appearance...","path":"IMG_4010.jpeg","imageCaption":"<div class=\"title\">The Yeti made an appearance...<\/div>","fileSize":149894,"name":"IMG_4010.jpeg","category":"image","camera":{"aperture":1.78,"exposureTime":"1\/60s","originalDate":"2024-07-13T12:51:23.0Z","cameraModel":"iPhone 15 Pro Max","location":{"altitude":"74.62 metres","latitude":"54° 24' 2.9\"","lat":54.400806,"long":-2.96445,"longitude":"-2° 57' 52.02\""},"focalLength35mm":"33mm","resolution":"4284 x 5712","cameraMake":"Apple","isoEquivalent":250,"flash":"Flash did not fire","focalLength":"7mm"}},{"path":"IMG_4011.jpeg","image":{"path":"slides\/IMG_4011.jpeg","width":600,"height":800},"regions":"[\";0.909;0.727;0.091;0.219\"]","thumb":{"path":"thumbs\/IMG_4011.jpeg","width":212,"height":170},"fileSize":274131,"photodata":"<dl><dt>Original Date<\/dt><dd>7\/13\/24, 12:51 PM<\/dd><dt>Make<\/dt><dd>Apple<\/dd><dt>Camera<\/dt><dd>iPhone 15 Pro Max<\/dd><dt>Lens Model<\/dt><dd>iPhone 15 Pro Max back triple camera 6.765mm f\/1.78<\/dd><dt>Focal Length (35mm)<\/dt><dd>33mm<\/dd><dt>Metering Mode<\/dt><dd>Spot<\/dd><dt>ISO Equivalent<\/dt><dd>250<\/dd><dt>Exposure Time<\/dt><dd>1\/60s<\/dd><dt>Aperture<\/dt><dd>ƒ\/1.8<\/dd><dt>Exposure bias<\/dt><dd>0 EV<\/dd><dt>Exposure Program<\/dt><dd>Program normal<\/dd><dt>White balance<\/dt><dd>Auto white balance<\/dd><dt>Flash<\/dt><dd>Flash did not fire<\/dd><dt>Resolution<\/dt><dd>4284 x 5712<\/dd><\/dl>","name":"IMG_4011.jpeg","dates":{"dateTaken":1720900289},"fileDate":"2024-07-29T10:41:33.179Z","category":"image","camera":{"aperture":1.78,"exposureTime":"1\/60s","originalDate":"2024-07-13T12:51:29.0Z","cameraModel":"iPhone 15 Pro Max","location":{"altitude":"74.62 metres","latitude":"54° 24' 2.9\"","lat":54.400806,"long":-2.96445,"longitude":"-2° 57' 52.02\""},"focalLength35mm":"33mm","resolution":"4284 x 5712","cameraMake":"Apple","isoEquivalent":250,"flash":"Flash did not fire","focalLength":"7mm"}},{"path":"IMG_4013.jpeg","image":{"path":"slides\/IMG_4013.jpeg","width":579,"height":800},"thumb":{"path":"thumbs\/IMG_4013.jpeg","width":212,"height":170},"fileSize":185216,"photodata":"<dl><dt>Original Date<\/dt><dd>7\/13\/24, 12:55 PM<\/dd><dt>Make<\/dt><dd>Apple<\/dd><dt>Camera<\/dt><dd>iPhone 15 Pro Max<\/dd><dt>Lens Model<\/dt><dd>iPhone 15 Pro Max back triple camera 6.765mm f\/1.78<\/dd><dt>Focal Length (35mm)<\/dt><dd>96mm<\/dd><dt>Metering Mode<\/dt><dd>Multi-segment<\/dd><dt>ISO Equivalent<\/dt><dd>125<\/dd><dt>Exposure Time<\/dt><dd>1\/60s<\/dd><dt>Aperture<\/dt><dd>ƒ\/1.8<\/dd><dt>Exposure bias<\/dt><dd>0 EV<\/dd><dt>Exposure Program<\/dt><dd>Program normal<\/dd><dt>White balance<\/dt><dd>Auto white balance<\/dd><dt>Flash<\/dt><dd>Flash did not fire<\/dd><dt>Resolution<\/dt><dd>2535 x 3502<\/dd><\/dl>","name":"IMG_4013.jpeg","dates":{"dateTaken":1720900531},"fileDate":"2024-07-29T10:41:33.259Z","category":"image","camera":{"aperture":1.78,"exposureTime":"1\/60s","originalDate":"2024-07-13T12:55:31.0Z","cameraModel":"iPhone 15 Pro Max","location":{"altitude":"76.91 metres","latitude":"54° 24' 40.28\"","lat":54.41119,"long":-2.957233,"longitude":"-2° 57' 26.04\""},"focalLength35mm":"96mm","resolution":"2535 x 3502","cameraMake":"Apple","isoEquivalent":125,"flash":"Flash did not fire","focalLength":"7mm"}},{"path":"IMG_4015.jpeg","image":{"path":"slides\/IMG_4015.jpeg","width":600,"height":800},"thumb":{"path":"thumbs\/IMG_4015.jpeg","width":212,"height":170},"fileSize":219329,"photodata":"<dl><dt>Original Date<\/dt><dd>7\/13\/24, 12:57 PM<\/dd><dt>Make<\/dt><dd>Apple<\/dd><dt>Camera<\/dt><dd>iPhone 15 Pro Max<\/dd><dt>Lens Model<\/dt><dd>iPhone 15 Pro Max back triple camera 2.22mm f\/2.2<\/dd><dt>Focal Length (35mm)<\/dt><dd>19mm<\/dd><dt>Metering Mode<\/dt><dd>Multi-segment<\/dd><dt>ISO Equivalent<\/dt><dd>50<\/dd><dt>Exposure Time<\/dt><dd>1\/99s<\/dd><dt>Aperture<\/dt><dd>ƒ\/2.2<\/dd><dt>Exposure bias<\/dt><dd>0 EV<\/dd><dt>Exposure Program<\/dt><dd>Program normal<\/dd><dt>White balance<\/dt><dd>Auto white balance<\/dd><dt>Flash<\/dt><dd>Flash did not fire<\/dd><dt>Resolution<\/dt><dd>4032 x 3024<\/dd><\/dl>","name":"IMG_4015.jpeg","dates":{"dateTaken":1720900657},"fileDate":"2024-07-29T10:41:33.289Z","category":"image","camera":{"aperture":2.2,"exposureTime":"1\/99s","originalDate":"2024-07-13T12:57:37.0Z","cameraModel":"iPhone 15 Pro Max","location":{"altitude":"74.93 metres","latitude":"54° 24' 2.89\"","lat":54.400803,"long":-2.964422,"longitude":"-2° 57' 51.92\""},"focalLength35mm":"19mm","resolution":"4032 x 3024","cameraMake":"Apple","isoEquivalent":50,"flash":"Flash did not fire","focalLength":"2mm"}},{"image":{"path":"slides\/IMG_4016.jpeg","width":1000,"height":750},"thumb":{"path":"thumbs\/IMG_4016.jpeg","width":212,"height":170},"thumbCaption":"<div class=\"title\">Much more impressive on the outside.<\/div>","photodata":"<dl><dt>Title<\/dt><dd>Much more impressive on the outside.<\/dd><dt>Original Date<\/dt><dd>7\/13\/24, 1:16 PM<\/dd><dt>Make<\/dt><dd>Apple<\/dd><dt>Camera<\/dt><dd>iPhone 15 Pro Max<\/dd><dt>Lens Model<\/dt><dd>iPhone 15 Pro Max back triple camera 6.765mm f\/1.78<\/dd><dt>Focal Length (35mm)<\/dt><dd>46mm<\/dd><dt>Metering Mode<\/dt><dd>Multi-segment<\/dd><dt>ISO Equivalent<\/dt><dd>80<\/dd><dt>Exposure Time<\/dt><dd>1\/3096s<\/dd><dt>Aperture<\/dt><dd>ƒ\/1.8<\/dd><dt>Exposure bias<\/dt><dd>0 EV<\/dd><dt>Exposure Program<\/dt><dd>Program normal<\/dd><dt>White balance<\/dt><dd>Auto white balance<\/dd><dt>Flash<\/dt><dd>Flash did not fire<\/dd><dt>Resolution<\/dt><dd>5712 x 4284<\/dd><\/dl>","dates":{"dateTaken":1720901784},"fileDate":"2024-07-29T10:41:33.340Z","title":"Much more impressive on the outside.","path":"IMG_4016.jpeg","imageCaption":"<div class=\"title\">Much more impressive on the outside.<\/div>","fileSize":333579,"name":"IMG_4016.jpeg","category":"image","camera":{"aperture":1.78,"exposureTime":"1\/3096s","originalDate":"2024-07-13T13:16:24.0Z","cameraModel":"iPhone 15 Pro Max","location":{"altitude":"80.01 metres","latitude":"54° 24' 0.47\"","lat":54.40013,"long":-2.965103,"longitude":"-2° 57' 54.37\""},"focalLength35mm":"46mm","resolution":"5712 x 4284","cameraMake":"Apple","isoEquivalent":80,"flash":"Flash did not fire","focalLength":"7mm"}},{"path":"IMG_4019.jpeg","image":{"path":"slides\/IMG_4019.jpeg","width":1000,"height":750},"thumb":{"path":"thumbs\/IMG_4019.jpeg","width":212,"height":170},"fileSize":499577,"photodata":"<dl><dt>Original Date<\/dt><dd>7\/13\/24, 1:32 PM<\/dd><dt>Make<\/dt><dd>Apple<\/dd><dt>Camera<\/dt><dd>iPhone 15 Pro Max<\/dd><dt>Lens Model<\/dt><dd>iPhone 15 Pro Max back triple camera 15.66mm f\/2.8<\/dd><dt>Focal Length (35mm)<\/dt><dd>206mm<\/dd><dt>Metering Mode<\/dt><dd>Multi-segment<\/dd><dt>ISO Equivalent<\/dt><dd>50<\/dd><dt>Exposure Time<\/dt><dd>1\/416s<\/dd><dt>Aperture<\/dt><dd>ƒ\/2.8<\/dd><dt>Exposure bias<\/dt><dd>0 EV<\/dd><dt>Exposure Program<\/dt><dd>Program normal<\/dd><dt>White balance<\/dt><dd>Auto white balance<\/dd><dt>Flash<\/dt><dd>Flash did not fire<\/dd><dt>Resolution<\/dt><dd>4032 x 3024<\/dd><\/dl>","name":"IMG_4019.jpeg","dates":{"dateTaken":1720902731},"fileDate":"2024-07-29T10:41:33.429Z","category":"image","camera":{"aperture":2.8,"exposureTime":"1\/416s","originalDate":"2024-07-13T13:32:11.0Z","cameraModel":"iPhone 15 Pro Max","location":{"altitude":"43.54 metres","latitude":"54° 24' 13.15\"","lat":54.403652,"long":-2.962892,"longitude":"-2° 57' 46.41\""},"focalLength35mm":"206mm","resolution":"4032 x 3024","cameraMake":"Apple","isoEquivalent":50,"flash":"Flash did not fire","focalLength":"16mm"}},{"path":"IMG_4020.jpeg","image":{"path":"slides\/IMG_4020.jpeg","width":1000,"height":750},"thumb":{"path":"thumbs\/IMG_4020.jpeg","width":212,"height":170},"fileSize":572060,"photodata":"<dl><dt>Original Date<\/dt><dd>7\/13\/24, 1:32 PM<\/dd><dt>Make<\/dt><dd>Apple<\/dd><dt>Camera<\/dt><dd>iPhone 15 Pro Max<\/dd><dt>Lens Model<\/dt><dd>iPhone 15 Pro Max back triple camera 2.22mm f\/2.2<\/dd><dt>Focal Length (35mm)<\/dt><dd>14mm<\/dd><dt>Metering Mode<\/dt><dd>Multi-segment<\/dd><dt>ISO Equivalent<\/dt><dd>40<\/dd><dt>Exposure Time<\/dt><dd>1\/241s<\/dd><dt>Aperture<\/dt><dd>ƒ\/2.2<\/dd><dt>Exposure bias<\/dt><dd>0 EV<\/dd><dt>Exposure Program<\/dt><dd>Program normal<\/dd><dt>White balance<\/dt><dd>Auto white balance<\/dd><dt>Flash<\/dt><dd>Flash did not fire<\/dd><dt>Resolution<\/dt><dd>4032 x 3024<\/dd><\/dl>","name":"IMG_4020.jpeg","dates":{"dateTaken":1720902748},"fileDate":"2024-07-29T10:41:33.460Z","category":"image","camera":{"aperture":2.2,"exposureTime":"1\/241s","originalDate":"2024-07-13T13:32:28.0Z","cameraModel":"iPhone 15 Pro Max","location":{"altitude":"43.68 metres","latitude":"54° 24' 13.16\"","lat":54.403656,"long":-2.962858,"longitude":"-2° 57' 46.29\""},"focalLength35mm":"14mm","resolution":"4032 x 3024","cameraMake":"Apple","isoEquivalent":40,"flash":"Flash did not fire","focalLength":"2mm"}},{"path":"IMG_4021.jpeg","image":{"path":"slides\/IMG_4021.jpeg","width":600,"height":800},"thumb":{"path":"thumbs\/IMG_4021.jpeg","width":212,"height":170},"fileSize":330467,"photodata":"<dl><dt>Original Date<\/dt><dd>7\/13\/24, 1:38 PM<\/dd><dt>Make<\/dt><dd>Apple<\/dd><dt>Camera<\/dt><dd>iPhone 15 Pro Max<\/dd><dt>Lens Model<\/dt><dd>iPhone 15 Pro Max back triple camera 2.22mm f\/2.2<\/dd><dt>Focal Length (35mm)<\/dt><dd>14mm<\/dd><dt>Metering Mode<\/dt><dd>Multi-segment<\/dd><dt>ISO Equivalent<\/dt><dd>40<\/dd><dt>Exposure Time<\/dt><dd>1\/128s<\/dd><dt>Aperture<\/dt><dd>ƒ\/2.2<\/dd><dt>Exposure bias<\/dt><dd>0 EV<\/dd><dt>Exposure Program<\/dt><dd>Program normal<\/dd><dt>White balance<\/dt><dd>Auto white balance<\/dd><dt>Flash<\/dt><dd>Flash did not fire<\/dd><dt>Resolution<\/dt><dd>4032 x 3024<\/dd><\/dl>","name":"IMG_4021.jpeg","dates":{"dateTaken":1720903093},"fileDate":"2024-07-29T10:41:33.490Z","category":"image","camera":{"aperture":2.2,"exposureTime":"1\/128s","originalDate":"2024-07-13T13:38:13.0Z","cameraModel":"iPhone 15 Pro Max","location":{"altitude":"44.69 metres","latitude":"54° 24' 12.74\"","lat":54.403538,"long":-2.963011,"longitude":"-2° 57' 46.84\""},"focalLength35mm":"14mm","resolution":"4032 x 3024","cameraMake":"Apple","isoEquivalent":40,"flash":"Flash did not fire","focalLength":"2mm"}},{"path":"IMG_4025.jpeg","image":{"path":"slides\/IMG_4025.jpeg","width":600,"height":800},"thumb":{"path":"thumbs\/IMG_4025.jpeg","width":212,"height":170},"fileSize":292335,"photodata":"<dl><dt>Original Date<\/dt><dd>7\/13\/24, 1:48 PM<\/dd><dt>Make<\/dt><dd>Apple<\/dd><dt>Camera<\/dt><dd>iPhone 15 Pro Max<\/dd><dt>Lens Model<\/dt><dd>iPhone 15 Pro Max back triple camera 6.765mm f\/1.78<\/dd><dt>Focal Length (35mm)<\/dt><dd>24mm<\/dd><dt>Metering Mode<\/dt><dd>Multi-segment<\/dd><dt>ISO Equivalent<\/dt><dd>80<\/dd><dt>Exposure Time<\/dt><dd>1\/4950s<\/dd><dt>Aperture<\/dt><dd>ƒ\/1.8<\/dd><dt>Exposure bias<\/dt><dd>0 EV<\/dd><dt>Exposure Program<\/dt><dd>Program normal<\/dd><dt>White balance<\/dt><dd>Auto white balance<\/dd><dt>Flash<\/dt><dd>Flash did not fire<\/dd><dt>Resolution<\/dt><dd>5712 x 4284<\/dd><\/dl>","name":"IMG_4025.jpeg","dates":{"dateTaken":1720903689},"fileDate":"2024-07-29T10:41:33.529Z","category":"image","camera":{"aperture":1.78,"exposureTime":"1\/4950s","originalDate":"2024-07-13T13:48:09.0Z","cameraModel":"iPhone 15 Pro Max","location":{"altitude":"46.04 metres","latitude":"54° 24' 12.82\"","lat":54.40356,"long":-2.963078,"longitude":"-2° 57' 47.08\""},"focalLength35mm":"24mm","resolution":"5712 x 4284","cameraMake":"Apple","isoEquivalent":80,"flash":"Flash did not fire","focalLength":"7mm"}},{"path":"IMG_4027.jpeg","image":{"path":"slides\/IMG_4027.jpeg","width":600,"height":800},"thumb":{"path":"thumbs\/IMG_4027.jpeg","width":212,"height":170},"fileSize":302512,"photodata":"<dl><dt>Original Date<\/dt><dd>7\/13\/24, 1:48 PM<\/dd><dt>Make<\/dt><dd>Apple<\/dd><dt>Camera<\/dt><dd>iPhone 15 Pro Max<\/dd><dt>Lens Model<\/dt><dd>iPhone 15 Pro Max back triple camera 6.765mm f\/1.78<\/dd><dt>Focal Length (35mm)<\/dt><dd>99mm<\/dd><dt>Metering Mode<\/dt><dd>Multi-segment<\/dd><dt>ISO Equivalent<\/dt><dd>64<\/dd><dt>Exposure Time<\/dt><dd>1\/1458s<\/dd><dt>Aperture<\/dt><dd>ƒ\/1.8<\/dd><dt>Exposure bias<\/dt><dd>0 EV<\/dd><dt>Exposure Program<\/dt><dd>Program normal<\/dd><dt>White balance<\/dt><dd>Auto white balance<\/dd><dt>Flash<\/dt><dd>Flash did not fire<\/dd><dt>Resolution<\/dt><dd>4032 x 3024<\/dd><\/dl>","name":"IMG_4027.jpeg","dates":{"dateTaken":1720903723},"fileDate":"2024-07-29T10:41:33.590Z","category":"image","camera":{"aperture":1.78,"exposureTime":"1\/1458s","originalDate":"2024-07-13T13:48:43.0Z","cameraModel":"iPhone 15 Pro Max","location":{"altitude":"44.3 metres","latitude":"54° 24' 12.93\"","lat":54.40359,"long":-2.963003,"longitude":"-2° 57' 46.81\""},"focalLength35mm":"99mm","resolution":"4032 x 3024","cameraMake":"Apple","isoEquivalent":64,"flash":"Flash did not fire","focalLength":"7mm"}},{"image":{"path":"slides\/IMG_4029.jpeg","width":1000,"height":750},"thumb":{"path":"thumbs\/IMG_4029.jpeg","width":212,"height":170},"thumbCaption":"<div class=\"title\">Shot from the ferry ride back to the hotel... this is not our hotel.<\/div>","photodata":"<dl><dt>Title<\/dt><dd>Shot from the ferry ride back to the hotel... this is not our hotel.<\/dd><dt>Original Date<\/dt><dd>7\/13\/24, 2:38 PM<\/dd><dt>Make<\/dt><dd>Apple<\/dd><dt>Camera<\/dt><dd>iPhone 15 Pro Max<\/dd><dt>Lens Model<\/dt><dd>iPhone 15 Pro Max back triple camera 6.765mm f\/1.78<\/dd><dt>Focal Length (35mm)<\/dt><dd>95mm<\/dd><dt>Metering Mode<\/dt><dd>Multi-segment<\/dd><dt>ISO Equivalent<\/dt><dd>64<\/dd><dt>Exposure Time<\/dt><dd>1\/621s<\/dd><dt>Aperture<\/dt><dd>ƒ\/1.8<\/dd><dt>Exposure bias<\/dt><dd>0 EV<\/dd><dt>Exposure Program<\/dt><dd>Program normal<\/dd><dt>White balance<\/dt><dd>Auto white balance<\/dd><dt>Flash<\/dt><dd>Flash did not fire<\/dd><dt>Resolution<\/dt><dd>4032 x 3024<\/dd><\/dl>","dates":{"dateTaken":1720906710},"fileDate":"2024-07-29T10:41:33.610Z","title":"Shot from the ferry ride back to the hotel... this is not our hotel.","path":"IMG_4029.jpeg","imageCaption":"<div class=\"title\">Shot from the ferry ride back to the hotel... this is not our hotel.<\/div>","fileSize":404790,"name":"IMG_4029.jpeg","category":"image","camera":{"aperture":1.78,"exposureTime":"1\/621s","originalDate":"2024-07-13T14:38:30.0Z","cameraModel":"iPhone 15 Pro Max","location":{"altitude":"43 metres","latitude":"54° 25' 8.9\"","lat":54.41914,"long":-2.963222,"longitude":"-2° 57' 47.6\""},"focalLength35mm":"95mm","resolution":"4032 x 3024","cameraMake":"Apple","isoEquivalent":64,"flash":"Flash did not fire","focalLength":"7mm"}}],"name":"Ambleside, Lower Lake District","dates":{"dateRange":{"0":1720895887,"1":1720989383}},"fileDate":"2024-07-30T14:04:28.49Z"}